Testing/decoder/dec_if2_4.v
module dec_if2_4(input [1:0] in,
                 input en,
                 output reg [3:0] out)
;

always @ (*) begin
if (!en) begin

out = 4'b0000;

end else begin

if ( in == 2'b00 ) out = 4'b0001;
else if ( in == 2'b01 ) out = 4'b0010;
else if ( in == 2'b10 ) out = 4'b0100;
else if ( in == 2'b11 ) out = 4'b1000;

end
end
endmodule

Testing/decoder/dec3_8_tb.v
`timescale 1 ns / 1 ps
module dec3_8_tb ();

reg [2:0] in;
wire [7:0] out;
integer i;
reg enn;

dec_if2_4 u0 (.in(in[1:0]), .en(enn), .out(out[3:0]));
dec_if2_4 u1 (.in(in[1:0]), .en(in[2]), .out(out[7:4]));

always @ (in) enn = ~in[2];

initial begin 
    in <= 3'b000;
    
    $monitor("in=%b out=%b", in, out);

    for (i = 0; i < 8; i = i + 1) begin
       #10 in <= i;
    end
end

initial begin
    $dumpfile ("dec3_8.vcd");
    $dumpvars (0,dec3_8_tb);
end

endmodule

Testing/decoder/dec3_8.vcd
$date
	Mon Aug 31 13:59:31 2026
$end
$version
	Icarus Verilog
$end
$timescale
	1ps
$end
$scope module dec3_8_tb $end
$var wire 8 ! out [7:0] $end
$var reg 1 " enn $end
$var reg 3 # in [2:0] $end
$var integer 32 $ i [31:0] $end
$scope module u0 $end
$var wire 1 " en $end
$var wire 2 % in [1:0] $end
$var reg 4 & out [3:0] $end
$upscope $end
$scope module u1 $end
$var wire 1 ' en $end
$var wire 2 ( in [1:0] $end
$var reg 4 ) out [3:0] $end
$upscope $end
$upscope $end
$enddefinitions $end
#0
$dumpvars
b0 )
b0 (
0'
b1 &
b0 %
b0 $
b0 #
1"
b1 !
$end
#10000
b1 $
#20000
b10 !
b10 &
b1 %
b1 (
b1 #
b10 $
#30000
b100 !
b100 &
b10 %
b10 (
b10 #
b11 $
#40000
b1000 !
b1000 &
b11 %
b11 (
b11 #
b100 $
#50000
b0 &
b10000 !
b1 )
0"
b0 %
b0 (
1'
b100 #
b101 $
#60000
b100000 !
b10 )
b1 %
b1 (
b101 #
b110 $
#70000
b1000000 !
b100 )
b10 %
b10 (
b110 #
b111 $
#80000
b10000000 !
b1000 )
b11 %
b11 (
b111 #
b1000 $
