Testing/decoder/dec_sprinkler.v
module dec_if2_4(input [1:0] in,
                 input en,
                 output reg [3:0] out)
;

always @ (*) begin
if (!en) begin

out = 4'b0000;

end else begin

if ( in == 2'b00 ) out = 4'b0001;
else if ( in == 2'b01 ) out = 4'b0010;
else if ( in == 2'b10 ) out = 4'b0100;
else if ( in == 2'b11 ) out = 4'b1000;

end
end
endmodule

module dec3_8 ( input [2:0] in,
                output [7:0] out)
;

wire enn;

assign enn = ~in[2];

dec_if2_4 u0 (.in(in[1:0]), .en(enn), .out(out[3:0]));
dec_if2_4 u1 (.in(in[1:0]), .en(in[2]), .out(out[7:4]));

endmodule

module dec_sprinkler (  input S, M, T, H,
                        output S1, S2)
;

wire [7:0] out;

dec3_8 d0 (.in({S,M,T}), .out(out));

assign S1 = out[5] | (out[7] & H);
assign S2 = out[0] | out[1];


endmodule

Testing/decoder/dec_sprinkler_tb.v
`timescale 1 ns / 1 ps
module dec_sprinkler_tb ();

reg S, M, T, H;
wire S1, S2;
integer i;

dec_sprinkler d1 (.S(S), .M(M), .T(T), .H(H), .S1(S1), .S2(S2));

initial begin 
    {S, M, T, H} <= 4'b0110;
    
    $monitor("S=%b M=%b T=%b H=%b S1=%b S2=%b", S, M, T, H, S1, S2);

    for (i = 0; i < 16; i = i + 1) begin
       #10 {S, M, T, H} <= i;
    end
end

initial begin
    $dumpfile ("dec_sprinkler.vcd");
    $dumpvars (0,dec_sprinkler_tb);
end

endmodule

Testing/decoder/dec_sprinkler.vcd
$date
	Mon Aug 31 16:21:22 2026
$end
$version
	Icarus Verilog
$end
$timescale
	1ps
$end
$scope module dec_sprinkler_tb $end
$var wire 1 ! S2 $end
$var wire 1 " S1 $end
$var reg 1 # H $end
$var reg 1 $ M $end
$var reg 1 % S $end
$var reg 1 & T $end
$var integer 32 ' i [31:0] $end
$scope module d1 $end
$var wire 1 # H $end
$var wire 1 $ M $end
$var wire 1 % S $end
$var wire 1 " S1 $end
$var wire 1 ! S2 $end
$var wire 1 & T $end
$var wire 8 ( out [7:0] $end
$scope module d0 $end
$var wire 1 ) enn $end
$var wire 3 * in [2:0] $end
$var wire 8 + out [7:0] $end
$scope module u0 $end
$var wire 1 ) en $end
$var wire 2 , in [1:0] $end
$var reg 4 - out [3:0] $end
$upscope $end
$scope module u1 $end
$var wire 1 . en $end
$var wire 2 / in [1:0] $end
$var reg 4 0 out [3:0] $end
$upscope $end
$upscope $end
$upscope $end
$upscope $end
$enddefinitions $end
#0
$dumpvars
b0 0
b11 /
0.
b1000 -
b11 ,
b1000 +
b11 *
1)
b1000 (
b0 '
1&
0%
1$
0#
0"
0!
$end
#10000
1!
b1 (
b1 +
b1 -
b0 ,
b0 /
0$
b0 *
0&
b1 '
#20000
1#
b10 '
#30000
b10 (
b10 +
b10 -
b1 ,
b1 /
b1 *
1&
0#
b11 '
#40000
1#
b100 '
#50000
0!
b100 (
b100 +
b100 -
b10 ,
b10 /
1$
b10 *
0&
0#
b101 '
#60000
1#
b110 '
#70000
b1000 (
b1000 +
b1000 -
b11 ,
b11 /
b11 *
1&
0#
b111 '
#80000
1#
b1000 '
#90000
0!
0)
b0 -
b10000 (
b10000 +
b1 0
1.
b0 ,
b0 /
1%
0$
b100 *
0&
0#
b1001 '
#100000
1#
b1010 '
#110000
1"
b100000 (
b100000 +
b10 0
b1 ,
b1 /
b101 *
1&
0#
b1011 '
#120000
1#
b1100 '
#130000
0"
b1000000 (
b1000000 +
b100 0
b10 ,
b10 /
1$
b110 *
0&
0#
b1101 '
#140000
1#
b1110 '
#150000
b10000000 (
b10000000 +
b1000 0
b11 ,
b11 /
b111 *
1&
0#
b1111 '
#160000
1"
1#
b10000 '
