Testing/d_ff/d_ff.v
module d_ff (   input d, clear, preset, clk,
                output reg q)
;

always @(posedge clk or negedge preset or negedge clear) begin // active-low control signals
    if (preset & !clear) q <= 0;
    else if (!preset & clear) q <= 1;
    else q <= d;
end

endmodule

Testing/d_ff/d_ff_tb.v
module d_ff_tb;

reg d, clear, preset, clk;
wire q;

d_ff u0 (.d(d),.clear(clear),.preset(preset),.clk(clk),.q(q));

always #10 clk = ~clk;

initial begin
    {clk, d} <= 0;
    {clear, preset} <= 2'b11;

    $monitor("time=%0t clear=%0b preset=%0b d=%0b q=%0b", $time, clear, preset, d, q);

    #5 clear <= 0;
    #5 clear <= 1; preset <= 0;
    #5 preset <= 1;

    #5 d <= 1;           
    #5 d <= 0; 
    #2 d <= 1;
    #8 d <= 0;
    #20 $finish;
end

initial begin
    $dumpfile ("d_ff.vcd");
    $dumpvars (0,d_ff_tb);
end

endmodule

Testing/d_ff/d_ff.vcd
$date
	Tue Oct 06 03:40:25 2026
$end
$version
	Icarus Verilog
$end
$timescale
	1s
$end
$scope module d_ff_tb $end
$var wire 1 ! q $end
$var reg 1 " clear $end
$var reg 1 # clk $end
$var reg 1 $ d $end
$var reg 1 % preset $end
$scope module u0 $end
$var wire 1 " clear $end
$var wire 1 # clk $end
$var wire 1 $ d $end
$var wire 1 % preset $end
$var reg 1 ! q $end
$upscope $end
$upscope $end
$enddefinitions $end
#0
$dumpvars
1%
0$
0#
1"
x!
$end
#5
0!
0"
#10
1!
0%
1"
1#
#15
1%
#20
1$
0#
#25
0$
#27
1$
#30
1#
#35
0$
#40
0#
#50
0!
1#
