Testing/updown_cntr/updown_cntr.v
module updown_cntr (input [3:0] din,
                    input clear, preset, clk, load, mode,
                    output reg [3:0] q)
;

always @(posedge clk) begin
    if (preset & !clear & load) q <= 4'b0;
    else if (!preset & clear & load) q <= 4'b1111;
    else if (preset & clear & !load) q <= din;
    else if (mode) q <= q + 1;
    else q <= q - 1;
end

endmodule

Testing/updown_cntr/updown_cntr_tb.v
module updown_cntr_tb;

reg [3:0] din;
reg clear, preset, clk, load, mode;
wire [3:0] q;

updown_cntr u0 (.din(din),.clear(clear),.preset(preset),.clk(clk),.load(load),.q(q),.mode(mode));

always #10 clk = ~clk;

initial begin

    {din, clk, mode} <= 5'b0;
    {clear, preset, load} <= 3'b111;

    $monitor("time=%0t clear=%b preset=%b load=%b mode=%b din=%b q=%b", $time, clear, preset, load, mode, din, q);

    #5 clear <= 0;
    #10 clear <= 1; preset <= 0;
    #20 preset <= 1; load <= 0; din <= 4'b1001;
    #20 load <= 1; mode <= 0;
    #400 mode <= 1;
    #400 $finish;
end

initial begin
    $dumpfile ("updown_cntr.vcd");
    $dumpvars (0,updown_cntr_tb);
end

endmodule

Testing/updown_cntr/updown_cntr.vcd
$date
	Tue Oct 06 04:51:23 2026
$end
$version
	Icarus Verilog
$end
$timescale
	1s
$end
$scope module updown_cntr_tb $end
$var wire 4 ! q [3:0] $end
$var reg 1 " clear $end
$var reg 1 # clk $end
$var reg 4 $ din [3:0] $end
$var reg 1 % load $end
$var reg 1 & mode $end
$var reg 1 ' preset $end
$scope module u0 $end
$var wire 1 " clear $end
$var wire 1 # clk $end
$var wire 4 ( din [3:0] $end
$var wire 1 % load $end
$var wire 1 & mode $end
$var wire 1 ' preset $end
$var reg 4 ) q [3:0] $end
$upscope $end
$upscope $end
$enddefinitions $end
#0
$dumpvars
bx )
b0 (
1'
0&
1%
b0 $
0#
1"
bx !
$end
#5
0"
#10
b0 !
b0 )
1#
#15
0'
1"
#20
0#
#30
b1111 !
b1111 )
1#
#35
b1001 $
b1001 (
0%
1'
#40
0#
#50
b1001 !
b1001 )
1#
#55
1%
#60
0#
#70
b1000 !
b1000 )
1#
#80
0#
#90
b111 !
b111 )
1#
#100
0#
#110
b110 !
b110 )
1#
#120
0#
#130
b101 !
b101 )
1#
#140
0#
#150
b100 !
b100 )
1#
#160
0#
#170
b11 !
b11 )
1#
#180
0#
#190
b10 !
b10 )
1#
#200
0#
#210
b1 !
b1 )
1#
#220
0#
#230
b0 !
b0 )
1#
#240
0#
#250
b1111 !
b1111 )
1#
#260
0#
#270
b1110 !
b1110 )
1#
#280
0#
#290
b1101 !
b1101 )
1#
#300
0#
#310
b1100 !
b1100 )
1#
#320
0#
#330
b1011 !
b1011 )
1#
#340
0#
#350
b1010 !
b1010 )
1#
#360
0#
#370
b1001 !
b1001 )
1#
#380
0#
#390
b1000 !
b1000 )
1#
#400
0#
#410
b111 !
b111 )
1#
#420
0#
#430
b110 !
b110 )
1#
#440
0#
#450
b101 !
b101 )
1#
#455
1&
#460
0#
#470
b110 !
b110 )
1#
#480
0#
#490
b111 !
b111 )
1#
#500
0#
#510
b1000 !
b1000 )
1#
#520
0#
#530
b1001 !
b1001 )
1#
#540
0#
#550
b1010 !
b1010 )
1#
#560
0#
#570
b1011 !
b1011 )
1#
#580
0#
#590
b1100 !
b1100 )
1#
#600
0#
#610
b1101 !
b1101 )
1#
#620
0#
#630
b1110 !
b1110 )
1#
#640
0#
#650
b1111 !
b1111 )
1#
#660
0#
#670
b0 !
b0 )
1#
#680
0#
#690
b1 !
b1 )
1#
#700
0#
#710
b10 !
b10 )
1#
#720
0#
#730
b11 !
b11 )
1#
#740
0#
#750
b100 !
b100 )
1#
#760
0#
#770
b101 !
b101 )
1#
#780
0#
#790
b110 !
b110 )
1#
#800
0#
#810
b111 !
b111 )
1#
#820
0#
#830
b1000 !
b1000 )
1#
#840
0#
#850
b1001 !
b1001 )
1#
