Testing/encoder/Enc16_4.v
module Enc16_4 (input [15:0] KEY,
                output [3:0] CODE)
;

integer i, count;

always @ (*) begin

i = KEY;
count = -1; 

while (i != 0) begin
        i = (i >> 1);
        count = count + 1;
    end

// for (i = 0; i < 16; i = i + 1) begin
//         if (KEY[i]) CODE = i[3:0];
//     end

end

assign CODE = KEY ? count : 4'b0;

endmodule

Testing/encoder/Enc16_4_tb.v
`timescale 1 ns / 1 ps
module Enc16_4_tb ();

reg [15:0] KEY;
wire [3:0] CODE;
integer i;

Enc16_4 u0 (.KEY(KEY), .CODE(CODE));

initial begin

    KEY <= 16'b1;
    $monitor("KEY=%b CODE=%b", KEY, CODE);

    for (i = 0; i < 16; i = i + 1) begin
        KEY <= (1 << i); #10;
    end

end

initial begin
    $dumpfile ("Enc16_4.vcd");
    $dumpvars (0,Enc16_4_tb);
end

endmodule

Testing/encoder/Enc16_4.vcd
$date
	Mon Aug 31 06:43:12 2026
$end
$version
	Icarus Verilog
$end
$timescale
	1ps
$end
$scope module Enc16_4_tb $end
$var wire 4 ! CODE [3:0] $end
$var reg 16 " KEY [15:0] $end
$var integer 32 # i [31:0] $end
$scope module u0 $end
$var wire 16 $ KEY [15:0] $end
$var wire 4 % CODE [3:0] $end
$var integer 32 & count [31:0] $end
$var integer 32 ' i [31:0] $end
$upscope $end
$upscope $end
$enddefinitions $end
#0
$dumpvars
b0 '
b0 &
b0 %
b1 $
b0 #
b1 "
b0 !
$end
#10000
b1 !
b1 %
b1 &
b0 '
b10 "
b10 $
b1 #
#20000
b10 !
b10 %
b10 &
b0 '
b100 "
b100 $
b10 #
#30000
b11 !
b11 %
b11 &
b0 '
b1000 "
b1000 $
b11 #
#40000
b100 !
b100 %
b100 &
b0 '
b10000 "
b10000 $
b100 #
#50000
b101 !
b101 %
b101 &
b0 '
b100000 "
b100000 $
b101 #
#60000
b110 !
b110 %
b110 &
b0 '
b1000000 "
b1000000 $
b110 #
#70000
b111 !
b111 %
b111 &
b0 '
b10000000 "
b10000000 $
b111 #
#80000
b1000 !
b1000 %
b1000 &
b0 '
b100000000 "
b100000000 $
b1000 #
#90000
b1001 !
b1001 %
b1001 &
b0 '
b1000000000 "
b1000000000 $
b1001 #
#100000
b1010 !
b1010 %
b1010 &
b0 '
b10000000000 "
b10000000000 $
b1010 #
#110000
b1011 !
b1011 %
b1011 &
b0 '
b100000000000 "
b100000000000 $
b1011 #
#120000
b1100 !
b1100 %
b1100 &
b0 '
b1000000000000 "
b1000000000000 $
b1100 #
#130000
b1101 !
b1101 %
b1101 &
b0 '
b10000000000000 "
b10000000000000 $
b1101 #
#140000
b1110 !
b1110 %
b1110 &
b0 '
b100000000000000 "
b100000000000000 $
b1110 #
#150000
b1111 !
b1111 %
b1111 &
b0 '
b1000000000000000 "
b1000000000000000 $
b1111 #
#160000
b10000 #
