Testing/demux/demux1_4.v
module demux1_4 (   input [7:0] data,
                    input [1:0] S,
                    output [7:0] Ch0, Ch1, Ch2, Ch3)
;

assign Ch0 = (S == 2'b00) ? data : 0;
assign Ch1 = (S == 2'b01) ? data : 0;
assign Ch2 = (S == 2'b10) ? data : 0;
assign Ch3 = (S == 2'b11) ? data : 0;

endmodule

Testing/demux/demux1_4_tb.v
`timescale 1 ns / 1 ps
module demux1_4_tb ();

reg [7:0] data;
reg [1:0] S;
wire [7:0] Ch0, Ch1, Ch2, Ch3;
integer i;

demux1_4 u0 (.data(data), .S(S), .Ch0(Ch0), .Ch1(Ch1), .Ch2(Ch2), .Ch3(Ch3));

initial begin

    {data, S} <= 10'b0;
    $monitor("data=%b S=%b Ch0=%b Ch1=%b Ch2=%b Ch3=%b", data, S, Ch0, Ch1, Ch2, Ch3);

    for (i = 0; i < 8; i = i + 1) begin
        #10; data = $random;
             S = $random;
    end
    #10;
end

initial begin
    $dumpfile ("demux1_4.vcd");
    $dumpvars (0,demux1_4_tb);
end

endmodule

Testing/demux/demux1_4.vcd
$date
	Mon Aug 31 07:00:55 2026
$end
$version
	Icarus Verilog
$end
$timescale
	1ps
$end
$scope module demux1_4_tb $end
$var wire 8 ! Ch3 [7:0] $end
$var wire 8 " Ch2 [7:0] $end
$var wire 8 # Ch1 [7:0] $end
$var wire 8 $ Ch0 [7:0] $end
$var reg 2 % S [1:0] $end
$var reg 8 & data [7:0] $end
$var integer 32 ' i [31:0] $end
$scope module u0 $end
$var wire 2 ( S [1:0] $end
$var wire 8 ) data [7:0] $end
$var wire 8 * Ch3 [7:0] $end
$var wire 8 + Ch2 [7:0] $end
$var wire 8 , Ch1 [7:0] $end
$var wire 8 - Ch0 [7:0] $end
$upscope $end
$upscope $end
$enddefinitions $end
#0
$dumpvars
b0 -
b0 ,
b0 +
b0 *
b0 )
b0 (
b0 '
b0 &
b0 %
b0 $
b0 #
b0 "
b0 !
$end
#10000
b100100 #
b100100 ,
b1 '
b1 %
b1 (
b100100 &
b100100 )
#20000
b1001 !
b1001 *
b0 #
b0 ,
b10 '
b11 %
b11 (
b1001 &
b1001 )
#30000
b1101 #
b1101 ,
b0 !
b0 *
b11 '
b1 %
b1 (
b1101 &
b1101 )
#40000
b1100101 "
b1100101 +
b0 #
b0 ,
b100 '
b10 %
b10 (
b1100101 &
b1100101 )
#50000
b1 #
b1 ,
b0 "
b0 +
b101 '
b1 %
b1 (
b1 &
b1 )
#60000
b1110110 #
b1110110 ,
b110 '
b1110110 &
b1110110 )
#70000
b11101101 $
b11101101 -
b0 #
b0 ,
b111 '
b0 %
b0 (
b11101101 &
b11101101 )
#80000
b11111001 "
b11111001 +
b0 $
b0 -
b1000 '
b10 %
b10 (
b11111001 &
b11111001 )
