Testing/bcd_cntr/bcd_cntr.v
module t_ff (   input t, Clear, Clk,
                output reg Q)
;

always @(posedge Clk or negedge Clear) begin
    if (!Clear) Q <= 1'b0;
    else if (t) Q <= ~Q;
end

endmodule

module bcd_cntr (   input clear, clk,
                    output [3:0] q)
;

wire clr = (~(q[3] & q[1])) & clear;

t_ff u0 (.t(1'b1),.Clear(clr),.Clk(clk),.Q(q[0]));
t_ff u1 (.t(1'b1),.Clear(clr),.Clk(q[0]),.Q(q[1]));
t_ff u2 (.t(1'b1),.Clear(clr),.Clk(q[1]),.Q(q[2]));
t_ff u3 (.t(1'b1),.Clear(clr),.Clk(q[2]),.Q(q[3]));

endmodule

Testing/bcd_cntr/bcd_cntr_tb.v
module bcd_cntr_tb;

reg clear, clk;
wire [3:0] q;

bcd_cntr a0 (.clear(clear),.clk(clk),.q(q));

always #10 clk = ~clk;

initial begin

    {clear, clk} <= 2'b10;

    $monitor("time=%0t clear=%b q=%b", $time, clear, q);

    #5 clear <= 0;
    #10 clear <= 1'b1;
    #200 $finish;
end

initial begin
    $dumpfile ("bcd_cntr.vcd");
    $dumpvars (0,bcd_cntr_tb);
end

endmodule

Testing/bcd_cntr/bcd_cntr.vcd
$date
	Tue Oct 06 06:01:34 2026
$end
$version
	Icarus Verilog
$end
$timescale
	1s
$end
$scope module bcd_cntr_tb $end
$var wire 4 ! q [3:0] $end
$var reg 1 " clear $end
$var reg 1 # clk $end
$scope module a0 $end
$var wire 1 " clear $end
$var wire 1 # clk $end
$var wire 1 $ clr $end
$var wire 4 % q [3:0] $end
$scope module u0 $end
$var wire 1 $ Clear $end
$var wire 1 # Clk $end
$var wire 1 & t $end
$var reg 1 ' Q $end
$upscope $end
$scope module u1 $end
$var wire 1 $ Clear $end
$var wire 1 ( Clk $end
$var wire 1 ) t $end
$var reg 1 * Q $end
$upscope $end
$scope module u2 $end
$var wire 1 $ Clear $end
$var wire 1 + Clk $end
$var wire 1 , t $end
$var reg 1 - Q $end
$upscope $end
$scope module u3 $end
$var wire 1 $ Clear $end
$var wire 1 . Clk $end
$var wire 1 / t $end
$var reg 1 0 Q $end
$upscope $end
$upscope $end
$upscope $end
$enddefinitions $end
#0
$dumpvars
x0
1/
x.
x-
1,
x+
x*
1)
x(
x'
1&
bx %
x$
0#
1"
bx !
$end
#5
0(
0+
0.
0'
0*
0-
b0 !
b0 %
00
0$
0"
#10
1#
#15
1$
1"
#20
0#
#30
1$
00
0.
0-
0+
0*
0(
b0 !
b0 %
0'
1#
#40
0#
#50
1$
00
0.
0-
0+
0*
0(
b0 !
b0 %
0'
1#
#60
0#
#70
1$
00
0.
0-
0+
0*
0(
b0 !
b0 %
0'
1#
#80
0#
#90
1$
00
0.
0-
0+
0*
0(
b0 !
b0 %
0'
1#
#100
0#
#110
1$
00
0.
0-
0+
0*
0(
b0 !
b0 %
0'
1#
#120
0#
#130
1$
00
0.
0-
0+
0*
0(
b0 !
b0 %
0'
1#
#140
0#
#150
1$
00
0.
0-
0+
0*
0(
b0 !
b0 %
0'
1#
#160
0#
#170
1$
00
0.
0-
0+
0*
0(
b0 !
b0 %
0'
1#
#180
0#
#190
1$
00
0.
0-
0+
0*
0(
b0 !
b0 %
0'
1#
#200
0#
#210
1$
00
0.
0-
0+
0*
0(
b0 !
b0 %
0'
1#
