Testing/fullAdder.v
module fullAdder (   input a,
                        input b,
                        input cin,
                        output out,
                        output cout)
;

assign out = a ^ b ^ cin;
assign cout = ( a & b ) | ( a & cin ) | ( b & cin );
endmodule

Testing/add_sub_4bit/add_sub_4bitTB.v
`timescale 1ns / 1ps
module add_sub_4bitTB ();

reg signed [3:0] a;
reg signed [3:0] b;
reg cin;
reg SUB;
wire signed [3:0] out;
wire cout;
wire overflow;

reg signed [3:0] bn;
wire c1, c2, c3;

always @(SUB or b) begin
     cin = SUB;
     bn = b ^ {4{SUB}};
end

fullAdder fa1(.a(a[0]), .b(bn[0]), .cin(cin), .out(out[0]), .cout(c1));
fullAdder fa2(.a(a[1]), .b(bn[1]), .cin(c1), .out(out[1]), .cout(c2));
fullAdder fa3(.a(a[2]), .b(bn[2]), .cin(c2), .out(out[2]), .cout(c3));
fullAdder fa4(.a(a[3]), .b(bn[3]), .cin(c3), .out(out[3]), .cout(cout));

assign overflow = c3 ^ cout;

initial begin

    {a, b, bn, cin, SUB} <= 0;
    $monitor("a=%b b=%b SUB=%b out=%b overflow=%b", a, b, SUB, out, overflow);

    //test case 1
    #20; SUB <= 0; 
        a[3:0] <= 4'b0011; 
        b[3:0] <= 4'b0100;
    //test case 2
    #20; SUB <= 1;
        a[3:0] <= 4'b0011; 
        b[3:0] <= 4'b0100;
    //test case 3
    #20; SUB <= 0;
        a[3:0] <= 4'b0111; 
        b[3:0] <= 4'b0011;
    //test case 4
    #20; SUB <= 1;
        a[3:0] <= 4'b0000; 
        b[3:0] <= 4'b1000;
    //test case 5
    #20; SUB <= 0;
        a[3:0] <= 4'b1111; 
        b[3:0] <= 4'b1110;
    //test case 6
    #20; SUB <= 1;
        a[3:0] <= 4'b0111; 
        b[3:0] <= 4'b0011;
    //test case 7
    #20; SUB <= 1;
        a[3:0] <= 4'b1000; 
        b[3:0] <= 4'b0001;
end

initial begin
    $dumpfile ("add_sub_4bit.vcd");
    $dumpvars (0,add_sub_4bitTB);
end

endmodule

Testing/add_sub_4bit/add_sub_4bit.vcd
$date
	Tue Aug 18 07:16:56 2026
$end
$version
	Icarus Verilog
$end
$timescale
	1ps
$end
$scope module add_sub_4bitTB $end
$var wire 1 ! overflow $end
$var wire 4 " out [3:0] $end
$var wire 1 # cout $end
$var wire 1 $ c3 $end
$var wire 1 % c2 $end
$var wire 1 & c1 $end
$var reg 1 ' SUB $end
$var reg 4 ( a [3:0] $end
$var reg 4 ) b [3:0] $end
$var reg 4 * bn [3:0] $end
$var reg 1 + cin $end
$scope module fa1 $end
$var wire 1 , a $end
$var wire 1 - b $end
$var wire 1 + cin $end
$var wire 1 & cout $end
$var wire 1 . out $end
$upscope $end
$scope module fa2 $end
$var wire 1 / a $end
$var wire 1 0 b $end
$var wire 1 & cin $end
$var wire 1 % cout $end
$var wire 1 1 out $end
$upscope $end
$scope module fa3 $end
$var wire 1 2 a $end
$var wire 1 3 b $end
$var wire 1 % cin $end
$var wire 1 $ cout $end
$var wire 1 4 out $end
$upscope $end
$scope module fa4 $end
$var wire 1 5 a $end
$var wire 1 6 b $end
$var wire 1 $ cin $end
$var wire 1 # cout $end
$var wire 1 7 out $end
$upscope $end
$upscope $end
$enddefinitions $end
#0
$dumpvars
07
06
05
04
03
02
01
00
0/
0.
0-
0,
0+
b0 *
b0 )
b0 (
0'
0&
0%
0$
0#
b0 "
0!
$end
#20000
14
1.
b111 "
11
13
b100 *
1,
1/
b100 )
b11 (
#40000
1%
14
17
1&
1-
10
03
16
b1111 "
1.
b1011 *
1+
1'
#60000
1!
1$
17
04
06
b1010 "
0.
12
b11 *
0+
b11 )
b111 (
0'
#80000
01
13
b1000 "
0.
0,
0/
02
b111 *
1+
b1000 )
b0 (
1'
#100000
0!
1#
14
0&
0-
16
b1101 "
1.
1,
1/
12
15
b1110 *
0+
b1110 )
b1111 (
0'
#120000
14
1%
1&
07
00
b100 "
0.
05
b1100 *
1+
b11 )
b111 (
1'
#140000
1!
0$
0%
0&
1.
11
14
b111 "
07
10
b1110 *
0,
0/
02
15
b1 )
b1000 (
