Testing/mux/Mux_7seg.v
module MuxBeh4_1 (  input [3:0] in,
                    input [1:0] S,
                    output out)
;

assign out = (S == 2'd0) ? in[0] : (S == 2'd1) ? in[1] : (S == 2'd2) ? in[2] : (S == 2'd3) ? in[3] : 0;

endmodule

module Mux_7seg (   input [3:0] BCD,
                    output a, b, c, d, e, f, g)
;

wire w1, w2, w3, w4, w5, w6, w7, w8, w9;

assign w1 = BCD[0] & ~BCD[1];
assign w2 = ~BCD[0] & ~BCD[1];
assign w3 = BCD[0] ^ BCD[1];
assign w4 = ~BCD[0] & BCD[1];
assign w5 = ~(BCD[0] ^ BCD[1]);
assign w6 = BCD[0] | ~BCD[1];
assign w7 = BCD[0] | BCD[1];
assign w8 = BCD[0] & BCD[1];
assign w9 = ~BCD[1];

MuxBeh4_1 A (.in({1'b0, 1'b0, w2, w1}), .S(BCD[3:2]), .out(a));
MuxBeh4_1 B (.in({1'b0, 1'b0, w3, 1'b0}), .S(BCD[3:2]), .out(b));
MuxBeh4_1 C (.in({1'b0, 1'b0, 1'b0, w4}), .S(BCD[3:2]), .out(c));
MuxBeh4_1 D (.in({1'b0, BCD[0],w5, w1}), .S(BCD[3:2]), .out(d));
MuxBeh4_1 E (.in({1'b0, BCD[0], w6, BCD[0]}), .S(BCD[3:2]), .out(e));
MuxBeh4_1 F (.in({1'b0, 1'b0, w8, w7}), .S(BCD[3:2]), .out(f));
MuxBeh4_1 G (.in({1'b0, 1'b0, w8, w9}), .S(BCD[3:2]), .out(g));

endmodule

Testing/mux/Mux_7seg_tb.v
`timescale 1 ns / 1 ps
module Mux_7seg_tb ();

reg [3:0] BCD;
wire a, b, c, d, e, f, g;
integer i;

Mux_7seg u0 (.BCD(BCD), .a(a), .b(b), .c(c), .d(d), .e(e), .f(f), .g(g));

initial begin 
    BCD <= 0;

    $monitor("BCD=%b a=%b b=%b c=%b d=%b e=%b f=%b g=%b", BCD, a, b, c, d, e, f, g);
    
    for (i = 0; i < 10; i = i + 1) begin
        BCD <= i; #10; 
    end
end

initial begin
    $dumpfile ("Mux_7seg.vcd");
    $dumpvars (0,Mux_7seg_tb);
end

endmodule

Testing/mux/Mux_7seg.vcd
$date
	Mon Aug 31 17:31:04 2026
$end
$version
	Icarus Verilog
$end
$timescale
	1ps
$end
$scope module Mux_7seg_tb $end
$var wire 1 ! g $end
$var wire 1 " f $end
$var wire 1 # e $end
$var wire 1 $ d $end
$var wire 1 % c $end
$var wire 1 & b $end
$var wire 1 ' a $end
$var reg 4 ( BCD [3:0] $end
$var integer 32 ) i [31:0] $end
$scope module u0 $end
$var wire 4 * BCD [3:0] $end
$var wire 1 + w1 $end
$var wire 1 , w2 $end
$var wire 1 - w3 $end
$var wire 1 . w4 $end
$var wire 1 / w5 $end
$var wire 1 0 w6 $end
$var wire 1 1 w7 $end
$var wire 1 2 w8 $end
$var wire 1 3 w9 $end
$var wire 1 ! g $end
$var wire 1 " f $end
$var wire 1 # e $end
$var wire 1 $ d $end
$var wire 1 % c $end
$var wire 1 & b $end
$var wire 1 ' a $end
$scope module A $end
$var wire 2 4 S [1:0] $end
$var wire 4 5 in [3:0] $end
$var wire 1 ' out $end
$upscope $end
$scope module B $end
$var wire 2 6 S [1:0] $end
$var wire 4 7 in [3:0] $end
$var wire 1 & out $end
$upscope $end
$scope module C $end
$var wire 2 8 S [1:0] $end
$var wire 4 9 in [3:0] $end
$var wire 1 % out $end
$upscope $end
$scope module D $end
$var wire 2 : S [1:0] $end
$var wire 4 ; in [3:0] $end
$var wire 1 $ out $end
$upscope $end
$scope module E $end
$var wire 2 < S [1:0] $end
$var wire 4 = in [3:0] $end
$var wire 1 # out $end
$upscope $end
$scope module F $end
$var wire 2 > S [1:0] $end
$var wire 4 ? in [3:0] $end
$var wire 1 " out $end
$upscope $end
$scope module G $end
$var wire 2 @ S [1:0] $end
$var wire 4 A in [3:0] $end
$var wire 1 ! out $end
$upscope $end
$upscope $end
$upscope $end
$enddefinitions $end
#0
$dumpvars
b1 A
b0 @
b0 ?
b0 >
b10 =
b0 <
b10 ;
b0 :
b0 9
b0 8
b0 7
b0 6
b10 5
b0 4
13
02
01
10
1/
0.
0-
1,
0+
b0 *
b0 )
b0 (
0'
0&
0%
0$
0#
0"
1!
$end
#10000
1'
1$
1"
0,
0/
1#
b1 5
1+
b10 7
1-
b1 ?
11
b101 ;
b111 =
b1 (
b1 *
b1 )
#20000
1%
0'
0$
0!
b1 9
1.
0#
b0 5
0+
00
b0 A
03
b0 ;
b0 =
b10 (
b10 *
b10 )
#30000
0%
b0 9
0.
1/
1#
b0 7
0-
10
b11 ?
b10 A
12
b110 ;
b111 =
b11 (
b11 *
b11 )
#40000
1'
0"
b10 5
1,
01
b0 ?
02
b1 A
13
1$
0!
b1 4
b1 6
b1 8
b10 ;
b1 :
b10 =
b1 <
b1 >
b1 @
b100 (
b100 *
b100 )
#50000
0'
0$
1&
0,
0/
b1 5
1+
b10 7
1-
b1 ?
11
b101 ;
b111 =
b101 (
b101 *
b101 )
#60000
0#
b1 9
1.
b0 5
0+
00
b0 A
03
b0 ;
b0 =
b110 (
b110 *
b110 )
#70000
1$
0&
1#
1"
1!
b0 9
0.
1/
b0 7
0-
10
b11 ?
b10 A
12
b110 ;
b111 =
b111 (
b111 *
b111 )
#80000
0$
0#
b10 5
1,
0"
0!
01
b0 ?
02
b1 A
13
b10 4
b10 6
b10 8
b10 ;
b10 :
b10 =
b10 <
b10 >
b10 @
b1000 (
b1000 *
b1000 )
#90000
1$
1#
0,
0/
b1 5
1+
b10 7
1-
b1 ?
11
b101 ;
b111 =
b1001 (
b1001 *
b1001 )
#100000
b1010 )
