Testing/mux/MuxBeh4_1.v
module MuxBeh4_1 (  input [3:0] in,
                    input [1:0] S,
                    output out)
;

assign out = (S == 2'd0) ? in[0] : (S == 2'd1) ? in[1] : (S == 2'd2) ? in[2] : (S == 2'd3) ? in[3] : 0;

endmodule

Testing/mux/Mux4_1_tb.v
`timescale 1 ns / 1 ps
module Mux4_1_tb ();

reg [3:0] in;
reg [1:0] S;
wire out;
integer i;

MuxBeh4_1 u0 (.in(in), .S(S), .out(out));

initial begin 
    {in, S} <= 0;

    $monitor("in=%b S=%b out=%b", in, S, out);
    
    for (i = 0; i < 4; i = i + 1) begin
        S <= i; 
        in <= 0; #10;
        in [i] <= 1; #10; 
    end
end

initial begin
    $dumpfile ("MuxBeh4_1.vcd");
    $dumpvars (0,Mux4_1_tb);
end

endmodule

Testing/mux/MuxBeh4_1.vcd
$date
	Sun Aug 30 15:30:24 2026
$end
$version
	Icarus Verilog
$end
$timescale
	1ps
$end
$scope module Mux4_1_tb $end
$var wire 1 ! out $end
$var reg 2 " S [1:0] $end
$var reg 4 # in [3:0] $end
$var integer 32 $ i [31:0] $end
$scope module u0 $end
$var wire 2 % S [1:0] $end
$var wire 4 & in [3:0] $end
$var wire 1 ! out $end
$upscope $end
$upscope $end
$enddefinitions $end
#0
$dumpvars
b0 &
b0 %
b0 $
b0 #
b0 "
0!
$end
#10000
1!
b1 #
b1 &
#20000
0!
b0 #
b0 &
b1 "
b1 %
b1 $
#30000
1!
b10 #
b10 &
#40000
0!
b0 #
b0 &
b10 "
b10 %
b10 $
#50000
1!
b100 #
b100 &
#60000
0!
b0 #
b0 &
b11 "
b11 %
b11 $
#70000
1!
b1000 #
b1000 &
#80000
b100 $
