Testing/shift_reg/shift_reg.v
module d_ff (   input d, Clear, Clk,
                output reg Q)
;

always @(posedge Clk or negedge Clear) begin
    if (!Clear) Q <= 1'b0;
    else Q <= d;
end

endmodule

module shift_reg (  input clk, clear, dataIn, 
                    output [7:0] q)
;

d_ff f7 (.d(dataIn),.Clear(clear),.Clk(clk),.Q(q[7]));

genvar i;
generate
    for (i = 0; i < 7; i = i + 1) begin
        d_ff f (.d(q[i+1]),.Clear(clear),.Clk(clk),.Q(q[i]));
    end
endgenerate

endmodule

Testing/shift_reg/shift_reg_tb.v
module shift_reg_tb;

reg dataIn, clear, clk;
wire [7:0] q;

shift_reg u0 (.dataIn(dataIn),.clear(clear),.clk(clk),.q(q));

always #10 clk = ~clk;

initial begin

    {dataIn, clk} <= 2'b0;
    clear <= 1'b1;

    $monitor("time=%0t clear=%b dataIn=%b q=%b", $time, clear, dataIn, q);

    #5 clear <= 0;
    #10 clear <= 1; dataIn <= 1'b1;
    #20 dataIn <= 1'b1;
    #20 dataIn <= 1'b0;
    #20 dataIn <= 1'b1;
    #20 dataIn <= 1'b0;
    #20 dataIn <= 1'b0;
    #20 dataIn <= 1'b1;
    #20 dataIn <= 1'b1;
    #20 dataIn <= 1'b1; 
    #20 $finish;
end

initial begin
    $dumpfile ("shift_reg.vcd");
    $dumpvars (0,shift_reg_tb);
end

endmodule

Testing/shift_reg/shift_reg.vcd
$date
	Tue Oct 06 06:23:05 2026
$end
$version
	Icarus Verilog
$end
$timescale
	1s
$end
$scope module shift_reg_tb $end
$var wire 8 ! q [7:0] $end
$var reg 1 " clear $end
$var reg 1 # clk $end
$var reg 1 $ dataIn $end
$scope module u0 $end
$var wire 1 " clear $end
$var wire 1 # clk $end
$var wire 1 $ dataIn $end
$var wire 8 % q [7:0] $end
$scope begin genblk1[0] $end
$scope module f $end
$var wire 1 " Clear $end
$var wire 1 # Clk $end
$var wire 1 & d $end
$var reg 1 ' Q $end
$upscope $end
$upscope $end
$scope begin genblk1[1] $end
$scope module f $end
$var wire 1 " Clear $end
$var wire 1 # Clk $end
$var wire 1 ( d $end
$var reg 1 ) Q $end
$upscope $end
$upscope $end
$scope begin genblk1[2] $end
$scope module f $end
$var wire 1 " Clear $end
$var wire 1 # Clk $end
$var wire 1 * d $end
$var reg 1 + Q $end
$upscope $end
$upscope $end
$scope begin genblk1[3] $end
$scope module f $end
$var wire 1 " Clear $end
$var wire 1 # Clk $end
$var wire 1 , d $end
$var reg 1 - Q $end
$upscope $end
$upscope $end
$scope begin genblk1[4] $end
$scope module f $end
$var wire 1 " Clear $end
$var wire 1 # Clk $end
$var wire 1 . d $end
$var reg 1 / Q $end
$upscope $end
$upscope $end
$scope begin genblk1[5] $end
$scope module f $end
$var wire 1 " Clear $end
$var wire 1 # Clk $end
$var wire 1 0 d $end
$var reg 1 1 Q $end
$upscope $end
$upscope $end
$scope begin genblk1[6] $end
$scope module f $end
$var wire 1 " Clear $end
$var wire 1 # Clk $end
$var wire 1 2 d $end
$var reg 1 3 Q $end
$upscope $end
$upscope $end
$scope module f7 $end
$var wire 1 " Clear $end
$var wire 1 # Clk $end
$var wire 1 $ d $end
$var reg 1 4 Q $end
$upscope $end
$upscope $end
$upscope $end
$enddefinitions $end
#0
$dumpvars
x4
x3
x2
x1
x0
x/
x.
x-
x,
x+
x*
x)
x(
x'
x&
bx %
0$
0#
1"
bx !
$end
#5
0&
0(
0*
0,
0.
00
02
0'
0)
0+
0-
0/
01
03
b0 !
b0 %
04
0"
#10
1#
#15
1$
1"
#20
0#
#30
12
b10000000 !
b10000000 %
14
1#
#40
0#
#50
10
b11000000 !
b11000000 %
13
1#
#55
0$
#60
0#
#70
1.
02
11
b1100000 !
b1100000 %
04
1#
#75
1$
#80
0#
#90
12
00
1,
14
03
b10110000 !
b10110000 %
1/
1#
#95
0$
#100
0#
#110
1*
0.
10
02
1-
01
13
b1011000 !
b1011000 %
04
1#
#120
0#
#130
00
1.
0,
1(
03
11
0/
b101100 !
b101100 %
1+
1#
#135
1$
#140
0#
#150
1&
0*
1,
0.
12
1)
0-
1/
01
b10010110 !
b10010110 %
14
1#
#160
0#
#170
10
0,
1*
0(
13
0/
1-
0+
b11001011 !
b11001011 %
1'
1#
#180
0#
#190
0&
1(
0*
1.
0)
1+
0-
b11100101 !
b11100101 %
11
1#
