Testing/t_ff/t_ff.v
module t_ff (   input t, clear, preset, clk,
                output reg q)
;

always @(negedge clk) begin
    if (preset & !clear) q <= 0;
    else if (!preset & clear) q <= 1;
    else if (t) q <= ~q;
end

endmodule

Testing/t_ff/t_ff_tb.v
module t_ff_tb;

reg t, clear, preset, clk;
wire q;

t_ff u0 (.t(t),.clear(clear),.preset(preset),.clk(clk),.q(q));

always #10 clk = ~clk;

initial begin
    {clk, t} <= 0;
    {clear, preset} <= 2'b11;

    $monitor("time=%0t clear=%0b preset=%0b t=%0b q=%0b", $time, clear, preset, t, q);

    #15 clear <= 0;
    #20 clear <= 1; preset <= 0;
    #10 preset <= 1;

    #4 t <= 1;           
    #5 t <= 0; 
    #2 t <= 1;
    #8 t <= 0;
    #1 t <= 1;
    #20 $finish;
end

initial begin
    $dumpfile ("t_ff.vcd");
    $dumpvars (0,t_ff_tb);
end

endmodule

Testing/t_ff/t_ff.vcd
$date
	Tue Oct 06 03:54:45 2026
$end
$version
	Icarus Verilog
$end
$timescale
	1s
$end
$scope module t_ff_tb $end
$var wire 1 ! q $end
$var reg 1 " clear $end
$var reg 1 # clk $end
$var reg 1 $ preset $end
$var reg 1 % t $end
$scope module u0 $end
$var wire 1 " clear $end
$var wire 1 # clk $end
$var wire 1 $ preset $end
$var wire 1 % t $end
$var reg 1 ! q $end
$upscope $end
$upscope $end
$enddefinitions $end
#0
$dumpvars
0%
1$
0#
1"
x!
$end
#10
1#
#15
0"
#20
0!
0#
#30
1#
#35
0$
1"
#40
1!
0#
#45
1$
#49
1%
#50
1#
#54
0%
#56
1%
#60
0!
0#
#64
0%
#65
1%
#70
1#
#80
1!
0#
