Testing/bin_incr4bit/bin_incr4bit.v
module inc (input [3:0] A,
            output [3:0] Y,
            output overflow)
;

wire [3:0] An;
wire w1, w2, w3, w4, w5, w6;

not(An[0], A[0]);
not(An[1], A[1]);
not(An[2], A[2]);
not(An[3], A[3]);

not(Y[0], A[0]);
xor(Y[1], A[0], A[1]);
and(w1, An[2], A[1], A[0]);
or(w2, An[0], An[1]);
and(w3, w2, A[2]);
or(Y[2], w1, w3);
and(w4, An[3], A[2], A[1], A[0]);
or(w5, An[2], An[1], An[0]);
and(w6, w5, A[3]);
or(Y[3], w4, w6);
and(overflow, A[0], A[1], A[2], A[3]);

endmodule

Testing/bin_incr4bit/bin_incr4bitTB.v

module bin_incr4bitTB ();

reg [3:0] A;
wire [3:0] Y;
wire overflow;
integer i;

inc inc0 (.A(A), .Y(Y), .overflow(overflow));

initial begin

    A <= 0;
    $monitor("time=%0t A=%b Y=%b overflow=%b", $time, A, Y, overflow);

    for (i = 0; i < 16; i = i + 1) begin
        #10; A <= i;
    end
end

initial begin
    $dumpfile ("bin_incr4bit.vcd");
    $dumpvars (0,bin_incr4bitTB);
end

endmodule

Testing/bin_incr4bit/bin_incr4bit.vcd
$date
	Sun Aug 30 18:02:49 2026
$end
$version
	Icarus Verilog
$end
$timescale
	1s
$end
$scope module bin_incr4bitTB $end
$var wire 1 ! overflow $end
$var wire 4 " Y [3:0] $end
$var reg 4 # A [3:0] $end
$var integer 32 $ i [31:0] $end
$scope module inc0 $end
$var wire 4 % A [3:0] $end
$var wire 1 ! overflow $end
$var wire 1 & w1 $end
$var wire 1 ' w2 $end
$var wire 1 ( w3 $end
$var wire 1 ) w4 $end
$var wire 1 * w5 $end
$var wire 1 + w6 $end
$var wire 4 , Y [3:0] $end
$var wire 4 - An [3:0] $end
$upscope $end
$upscope $end
$enddefinitions $end
#0
$dumpvars
b1111 -
b1 ,
0+
1*
0)
0(
1'
0&
b0 %
b0 $
b0 #
b1 "
0!
$end
#10
b1 $
#20
b1110 -
b10 "
b10 ,
b1 #
b1 %
b10 $
#30
b1101 -
b11 "
b11 ,
b10 #
b10 %
b11 $
#40
0'
b1100 -
b100 "
b100 ,
1&
b11 #
b11 %
b100 $
#50
1(
1'
b1011 -
b101 "
b101 ,
0&
b100 #
b100 %
b101 $
#60
b1010 -
b110 "
b110 ,
b101 #
b101 %
b110 $
#70
b1001 -
b111 "
b111 ,
b110 #
b110 %
b111 $
#80
0(
0'
0*
b1000 -
b1000 "
b1000 ,
1)
b111 #
b111 %
b1000 $
#90
1+
1'
1*
b111 -
b1001 "
b1001 ,
0)
b1000 #
b1000 %
b1001 $
#100
b110 -
b1010 "
b1010 ,
b1001 #
b1001 %
b1010 $
#110
b101 -
b1011 "
b1011 ,
b1010 #
b1010 %
b1011 $
#120
0'
b100 -
b1100 "
b1100 ,
1&
b1011 #
b1011 %
b1100 $
#130
1(
1'
b11 -
b1101 "
b1101 ,
0&
b1100 #
b1100 %
b1101 $
#140
b10 -
b1110 "
b1110 ,
b1101 #
b1101 %
b1110 $
#150
b1 -
b1111 "
b1111 ,
b1110 #
b1110 %
b1111 $
#160
0(
0+
0'
0*
b0 -
b0 "
b0 ,
1!
b1111 #
b1111 %
b10000 $
