Testing/jk_ff/jk_ff.v
module jk_ff (  input j, k, clear, preset, clk,
                output reg q)
;

always @(posedge clk or negedge preset or negedge clear) begin // active-low control signals
    if (preset & !clear) q <= 0;
    else if (!preset & clear) q <= 1;
    else begin case ({j,k})
                2'b00 : q <= q;
                2'b01 : q <= 0;
                2'b10 : q <= 1;
                2'b11 : q <= ~q;
        endcase
    end
end

endmodule

Testing/jk_ff/jk_ff_tb.v
module jk_ff_tb;

reg j, k, clear, preset, clk;
wire q;

jk_ff u0 (.j(j),.k(k),.clear(clear),.preset(preset),.clk(clk),.q(q));

always #10 clk = ~clk;

initial begin
    {clk, j, k} <= 0;
    {clear, preset} <= 2'b11;

    $monitor("time=%0t clear=%0b preset=%0b j=%0b k=%0b q=%0b", $time, clear, preset, j, k, q);

    #5 clear <= 0;
    #5 clear <= 1; preset <= 0;
    #5 preset <= 1;

    #5 {j, k} <= 2'b01;           
    #20 {j, k} <= 2'b10; 
    #20 {j, k} <= 2'b01;
    #80 {j, k} <= 2'b10;
    #20 $finish;
end

initial begin
    $dumpfile ("jk_ff.vcd");
    $dumpvars (0,jk_ff_tb);
end

endmodule

Testing/jk_ff/jk_ff.vcd
$date
	Tue Oct 06 04:05:12 2026
$end
$version
	Icarus Verilog
$end
$timescale
	1s
$end
$scope module jk_ff_tb $end
$var wire 1 ! q $end
$var reg 1 " clear $end
$var reg 1 # clk $end
$var reg 1 $ j $end
$var reg 1 % k $end
$var reg 1 & preset $end
$scope module u0 $end
$var wire 1 " clear $end
$var wire 1 # clk $end
$var wire 1 $ j $end
$var wire 1 % k $end
$var wire 1 & preset $end
$var reg 1 ! q $end
$upscope $end
$upscope $end
$enddefinitions $end
#0
$dumpvars
1&
0%
0$
0#
1"
x!
$end
#5
0!
0"
#10
1!
0&
1"
1#
#15
1&
#20
1%
0#
#30
0!
1#
#40
1$
0%
0#
#50
1!
1#
#60
0$
1%
0#
#70
0!
1#
#80
0#
#90
1#
#100
0#
#110
1#
#120
0#
#130
1#
#140
1$
0%
0#
#150
1!
1#
