Testing/tr_cntr/tr_cntr.v
module tr_cntr (input [7:0] din,
                input reset, clk, init,
                output reg [7:0] q)
;

wire q7n = ~q[7];
always @(posedge clk or negedge init or negedge reset) begin
    if (!reset & init) q <= 7'b0;
    else if (reset & !init) q <= din;
    else q <= {q[6:0],q7n};
end

endmodule

Testing/tr_cntr/tr_cntr_tb.v
module tr_cntr_tb;

reg [7:0] din;
reg reset, clk, init;
wire [7:0] q;

tr_cntr u0 (.din(din),.reset(reset),.clk(clk),.init(init),.q(q));

always #10 clk = ~clk;

initial begin

    {din, clk} <= 9'b0;
    {reset, init} <= 2'b11;

    $monitor("time=%0t reset=%b init=%b din=%b q=%b", $time, reset, init, din, q);

    #5 reset <= 0;
    #10 reset <= 1; init <= 0; din <= 8'b1011100;
    #20 init <= 1;
    #400 $finish;
end

initial begin
    $dumpfile ("tr_cntr.vcd");
    $dumpvars (0,tr_cntr_tb);
end

endmodule

Testing/tr_cntr/tr_cntr.vcd
$date
	Tue Oct 06 05:49:28 2026
$end
$version
	Icarus Verilog
$end
$timescale
	1s
$end
$scope module tr_cntr_tb $end
$var wire 8 ! q [7:0] $end
$var reg 1 " clk $end
$var reg 8 # din [7:0] $end
$var reg 1 $ init $end
$var reg 1 % reset $end
$scope module u0 $end
$var wire 1 " clk $end
$var wire 8 & din [7:0] $end
$var wire 1 $ init $end
$var wire 1 ' q7n $end
$var wire 1 % reset $end
$var reg 8 ( q [7:0] $end
$upscope $end
$upscope $end
$enddefinitions $end
#0
$dumpvars
bx (
x'
b0 &
1%
1$
b0 #
0"
bx !
$end
#5
1'
b0 !
b0 (
0%
#10
1"
#15
b1011100 !
b1011100 (
b1011100 #
b1011100 &
0$
1%
#20
0"
#30
1"
#35
1$
#40
0"
#50
0'
b10111001 !
b10111001 (
1"
#60
0"
#70
1'
b1110010 !
b1110010 (
1"
#80
0"
#90
0'
b11100101 !
b11100101 (
1"
#100
0"
#110
b11001010 !
b11001010 (
1"
#120
0"
#130
b10010100 !
b10010100 (
1"
#140
0"
#150
1'
b101000 !
b101000 (
1"
#160
0"
#170
b1010001 !
b1010001 (
1"
#180
0"
#190
0'
b10100011 !
b10100011 (
1"
#200
0"
#210
1'
b1000110 !
b1000110 (
1"
#220
0"
#230
0'
b10001101 !
b10001101 (
1"
#240
0"
#250
1'
b11010 !
b11010 (
1"
#260
0"
#270
b110101 !
b110101 (
1"
#280
0"
#290
b1101011 !
b1101011 (
1"
#300
0"
#310
0'
b11010111 !
b11010111 (
1"
#320
0"
#330
b10101110 !
b10101110 (
1"
#340
0"
#350
1'
b1011100 !
b1011100 (
1"
#360
0"
#370
0'
b10111001 !
b10111001 (
1"
#380
0"
#390
1'
b1110010 !
b1110010 (
1"
#400
0"
#410
0'
b11100101 !
b11100101 (
1"
#420
0"
#430
b11001010 !
b11001010 (
1"
